{"response": {"version": "0.1", "termsofService": "http://www.wunderground.com/weather/api/d/terms.html", "features": {"history": 1}}, "history": {"date": {"pretty": "March 24, 2018", "year": "2018", "mon": "03", "mday": "24", "hour": "08", "min": "30", "tzname": "Asia/Kolkata"}, "utcdate": {"pretty": "March 24, 2018", "year": "2018", "mon": "03", "mday": "24", "hour": "03", "min": "00", "tzname": "UTC"}, "observations": [{"date": {"pretty": "8:30 AM IST on March 24, 2018", "year": "2018", "mon": "03", "mday": "24", "hour": "08", "min": "30", "tzname": "Asia/Kolkata"}, "utcdate": {"pretty": "3:00 AM GMT on March 24, 2018", "year": "2018", "mon": "03", "mday": "24", "hour": "03", "min": "00", "tzname": "UTC"}, "tempm": "22", "tempi": "71", "dewptm": "11", "dewpti": "52", "hum": "41", "wspdm": "0.0", "wspdi": "0.0", "wgustm": "", "wgusti": "", "wdird": "270", "wdire": "West", "vism": "4", "visi": "2", "pressurem": "1014", "pressurei": "29.94", "windchillm": "-999", "windchilli": "-999", "heatindexm": "-9999", "heatindexi": "-9999", "precipm": "", "precipi": "", "conds": "", "icon": "", "fog": "0", "rain": "0", "snow": "0", "hail": "0", "thunder": "0", "tornado": "0", "metar": "AAXX 24033 42925 32996 02700 10216 20112 40137 333 20184 58016 555 10000"}, {"date": {"pretty": "5:30 PM IST on March 24, 2018", "year": "2018", "mon": "03", "mday": "24", "hour": "17", "min": "30", "tzname": "Asia/Kolkata"}, "utcdate": {"pretty": "12:00 PM GMT on March 24, 2018", "year": "2018", "mon": "03", "mday": "24", "hour": "12", "min": "00", "tzname": "UTC"}, "tempm": "36", "tempi": "97", "dewptm": "13", "dewpti": "55", "hum": "16", "wspdm": "", "wspdi": "", "wgustm": "", "wgusti": "", "wdird": "180", "wdire": "South", "vism": "10", "visi": "6", "pressurem": "1008", "pressurei": "29.75", "windchillm": "-999", "windchilli": "-999", "heatindexm": "-9999", "heatindexi": "-9999", "precipm": "", "precipi": "", "conds": "", "icon": "", "fog": "0", "rain": "0", "snow": "0", "hail": "0", "thunder": "0", "tornado": "0", "metar": "AAXX 24123 42925 32997 018// 10360 20130 40075 333 10386 58015"}], "dailysummary": []}}