{"history": {"date": {"pretty": "March 14, 2016", "year": "2016", "tzname": "Asia/Kolkata", "min": "30", "hour": "08", "mon": "03", "mday": "14"}, "utcdate": {"pretty": "March 14, 2016", "year": "2016", "tzname": "UTC", "min": "00", "hour": "03", "mon": "03", "mday": "14"}, "dailysummary": [], "observations": [{"date": {"pretty": "8:30 AM IST on March 14, 2016", "year": "2016", "tzname": "Asia/Kolkata", "min": "30", "hour": "08", "mon": "03", "mday": "14"}, "wdird": "", "hail": "0", "metar": "AAXX 14034 42851 32996 00000 10246 20172 40137 333 20174 58009 555 10000", "heatindexm": "-9999", "tempm": "25", "wdire": "", "wgusti": "", "windchilli": "-999", "precipm": "", "pressurei": "29.94", "visi": "2", "windchillm": "-999", "utcdate": {"pretty": "3:00 AM GMT on March 14, 2016", "year": "2016", "tzname": "UTC", "min": "00", "hour": "03", "mon": "03", "mday": "14"}, "dewptm": "17", "thunder": "0", "icon": "", "tempi": "76", "tornado": "0", "heatindexi": "-9999", "conds": "", "pressurem": "1014", "precipi": "", "snow": "0", "dewpti": "63", "wgustm": "", "hum": "55", "rain": "0", "vism": "4", "wspdm": "0.0", "fog": "0", "wspdi": "0.0"}, {"date": {"pretty": "5:30 PM IST on March 14, 2016", "year": "2016", "tzname": "Asia/Kolkata", "min": "30", "hour": "17", "mon": "03", "mday": "14"}, "wdird": "", "hail": "0", "metar": "AAXX 14124 42851 32697 00000 10340 20184 40081 333 10348 59007", "heatindexm": "-9999", "tempm": "34", "wdire": "", "wgusti": "", "windchilli": "-999", "precipm": "", "pressurei": "29.77", "visi": "6", "windchillm": "-999", "utcdate": {"pretty": "12:00 PM GMT on March 14, 2016", "year": "2016", "tzname": "UTC", "min": "00", "hour": "12", "mon": "03", "mday": "14"}, "dewptm": "18", "thunder": "0", "icon": "", "tempi": "93", "tornado": "0", "heatindexi": "-9999", "conds": "", "pressurem": "1008", "precipi": "", "snow": "0", "dewpti": "65", "wgustm": "", "hum": "30", "rain": "0", "vism": "10", "wspdm": "0.0", "fog": "0", "wspdi": "0.0"}]}, "response": {"version": "0.1", "termsofService": "http://www.wunderground.com/weather/api/d/terms.html", "features": {"history": 1}}}